landscape_widget/__init__.py
landscape_widget/_frontend.py
landscape_widget/_version.py
landscape_widget/landscape.py
landscape_widget/labextension/package.json
landscape_widget/labextension/static/122.9ae3f8117644f93e7b5d.js
landscape_widget/labextension/static/300.a328a9f5603f8aa15c51.js
landscape_widget/labextension/static/509.6ed434fd301ce6f8cb38.js
landscape_widget/labextension/static/788.00b85ececeaef3e1c83e.js
landscape_widget/labextension/static/906.0a89948d1926aacffab3.js
landscape_widget/labextension/static/remoteEntry.b7ec0f29067fe83977ec.js
landscape_widget/labextension/static/style.js
landscape_widget/labextension/static/third-party-licenses.json
landscape_widget/nbextension/extension.js
landscape_widget/nbextension/index.js
landscape_widget/nbextension/index.js.map
landscape_widget/tests/__init__.py
landscape_widget/tests/conftest.py
landscape_widget/tests/test_landscape.py
landscape_widget/tests/test_nbextension_path.py
landscape_widget-0.4.3.data/data/share/jupyter/labextensions/landscape-widget/package.json
landscape_widget-0.4.3.data/data/share/jupyter/labextensions/landscape-widget/static/122.9ae3f8117644f93e7b5d.js
landscape_widget-0.4.3.data/data/share/jupyter/labextensions/landscape-widget/static/300.a328a9f5603f8aa15c51.js
landscape_widget-0.4.3.data/data/share/jupyter/labextensions/landscape-widget/static/509.6ed434fd301ce6f8cb38.js
landscape_widget-0.4.3.data/data/share/jupyter/labextensions/landscape-widget/static/788.00b85ececeaef3e1c83e.js
landscape_widget-0.4.3.data/data/share/jupyter/labextensions/landscape-widget/static/906.0a89948d1926aacffab3.js
landscape_widget-0.4.3.data/data/share/jupyter/labextensions/landscape-widget/static/remoteEntry.b7ec0f29067fe83977ec.js
landscape_widget-0.4.3.data/data/share/jupyter/labextensions/landscape-widget/static/style.js
landscape_widget-0.4.3.data/data/share/jupyter/labextensions/landscape-widget/static/third-party-licenses.json
landscape_widget-0.4.3.dist-info/METADATA
landscape_widget-0.4.3.dist-info/WHEEL
landscape_widget-0.4.3.dist-info/licenses/LICENSE.txt
landscape_widget-0.4.3.dist-info/licenses/NOTICE
landscape_widget-0.4.3.dist-info/RECORD
